{
  "domain": "resume.troyv.dev",
  "website": "https://resume.troyv.dev/",
  "title": "Résumé",
  "description": "An online version of my résumé. Easily printable!.",
  "meta": {
    "name": "Troy Vassalotti",
    "mastodon": "@rest@fosstodon.org",
    "pronouns": "he/him/his",
    "picture": "cover.jpg",
    "title": "Web Developer",
    "location": "Maryland, US",
    "contact": {
      "email": "troy@troyv.dev",
      "website": "https://www.troyv.dev/"
    },
    "socials": {
      "hideonprint": true,
      "accounts": {
        "github": "https://github.com/troyvassalotti",
        "linkedin": "https://linkedin.com/in/troyvassalotti"
      }
    }
  },
  "experience": [
    {
      "job": "Bakery Associate",
      "employer": {
        "name": "Weis Markets",
        "city": "Damascus, MD",
        "website": "https://www.weismarkets.com/"
      },
      "dates": {
        "start": "2013-03-01",
        "end": "2017-08-24"
      },
      "responsibilities": "I worked in a bakery, waking up early to decorate donuts and bake bread, amongst other goods.",
      "hideonprint": true
    },
    {
      "job": "Songwriter, Guitarist",
      "employer": {
        "name": "Front Royal",
        "city": "Baltimore, MD",
        "website": "https://www.frontroyalband.com/"
      },
      "dates": {
        "start": "2014-04-01"
      },
      "responsibilities": "We've completed two independent tours across 11 states. I design, develop, and maintain our website; built with Eleventy and hosted on Netlify via git.",
      "hideonprint": true
    },
    {
      "job": "Intern",
      "employer": {
        "name": "Terra's Kitchen",
        "city": "Baltimore, MD",
        "website": "https://thedailyrecord.com/2019/09/25/baltimore-based-terras-kitchen-files-for-bankruptcy/"
      },
      "dates": {
        "start": "2017-05-30",
        "end": "2017-09-01"
      },
      "responsibilities": "I was responsible for cataloging our inventory of content and creative works to help the team quickly find assets.",
      "hideonprint": true
    },
    {
      "job": "Marketing Production Coordinator",
      "employer": {
        "name": "Terra's Kitchen",
        "city": "Baltimore, MD",
        "website": "https://thedailyrecord.com/2019/09/25/baltimore-based-terras-kitchen-files-for-bankruptcy/"
      },
      "dates": {
        "start": "2017-09-02",
        "end": "2019-08-28"
      },
      "responsibilities": "I managed the email channel, driving conversions and engagement. I designed and built mobile-responsive email templates, automated workflows, managed lists, and improved our HubSpot deliverability score from a 1 to a 67 (avg. score = 50), greatly improving channel effectiveness. I headed SEO, including maintaining our keyword database and Moz Pro reporting."
    },
    {
      "job": "Senior Technical and Compliance Specialist",
      "employer": {
        "name": "NewMarket Group",
        "city": "Baltimore, MD",
        "website": "https://www.newmarkethealth.com/"
      },
      "dates": {
        "start": "2019-10-14",
        "end": "2022-03-25"
      },
      "responsibilities": "I conducted technical reviews for web-based products and promotions, ensuring best practices in performance and accessibility. I monitored the health of our domains, acting on any blacklisting reports and working with the marketing team to address compliance issues on the part of our affiliates. I stayed up to date on the latest developments in the industry, helping my teams stay informed on upcoming changes or optimization opportunities."
    },
    {
      "job": "Web Developer/Designer",
      "employer": {
        "name": "Goucher College",
        "city": "Baltimore, MD",
        "website": "https://www.goucher.edu/"
      },
      "dates": {
        "start": "2021-06-07",
        "end": "2023-12-21"
      },
      "partTime": true,
      "responsibilities": "I managed a WordPress multisite network for the arts department, designing and developing sites, PHP templates, and child themes to meet the needs of the department. Students and staff contribute to the site, so I kept structured documentation in order for everyone to be able to complete their work as needed."
    },
    {
      "job": "Associate Software Engineer",
      "employer": {
        "name": "T. Rowe Price",
        "city": "Baltimore, MD",
        "website": "https://www.troweprice.com/"
      },
      "dates": {
        "start": "2022-03-28",
        "end": "2024-01-01"
      },
      "responsibilities": "I developed web components for the Beacon Design System, working closely with the design team to implement components according to the design specifications. I assisted teams consuming the web components in their application at all stages of the adoption process. Notable projects include creating the architecture for components such as Tables, Data Visualization, architecting the Beacon CSS utility framework, refactoring our Style Dictionary build to support modern and cross platform design tokens, and devising a deprecation strategy for component properties and style tokens when structural changes impact those initial implementations."
    },
    {
      "job": "Software Engineer, Tech Lead",
      "employer": {
        "name": "T. Rowe Price",
        "city": "Baltimore, MD",
        "website": "https://www.troweprice.com/"
      },
      "dates": {
        "start": "2024-01-01"
      },
      "responsibilities": "I serve as the Tech Lead for the Beacon Web Team. I continue to develop components for the Beacon Design System while also helping to shape the future of the system through assisting with the project roadmap and guiding the team along in defining a strong set of patterns that help make our components the best they can be for our users."
    }
  ],
  "education": [
    {
      "school": {
        "name": "Towson University",
        "city": "Towson, MD",
        "website": "https://www.towson.edu"
      },
      "degree": "B.S., Business Administration",
      "dates": {
        "start": "2013-08-24",
        "end": "2017-08-07"
      }
    }
  ],
  "skills": [
    "HTML, CSS, JavaScript",
    "Vue",
    "React",
    "Data Visualization",
    "Git",
    "WordPress",
    "PHP",
    "End-to-End Testing, QA",
    "CI/CD"
  ],
  "certifications": [
    {
      "issuer": "Moz",
      "types": ["SEO Fundamentals"]
    },
    {
      "issuer": "HubSpot",
      "types": ["Inbound, Email, & Content Marketing"]
    },
    {
      "issuer": "Google",
      "types": ["Advanced Google Analytics", "Google Tag Manager Fundamentals"]
    },
    {
      "issuer": "freeCodeCamp.org",
      "types": [
        "Responsive Web Design",
        "JavaScript Algorithms and Data Structures",
        "Front End Frameworks",
        "Data Visualization",
        "APIs and Microservices"
      ]
    }
  ],
  "interests": {
    "blurb": "When I'm not writing code, I'm either writing music or learning about literally anything new.",
    "links": [
      {
        "name": "Front Royal",
        "url": "https://www.frontroyalband.com/",
        "desc": "A punk band with a splash of indie."
      },
      {
        "name": "troyalllowercase",
        "url": "https://troyalllowercase.bandcamp.com/",
        "desc": "My solo project where I do whatever I want."
      },
      {
        "name": "charmCityJS",
        "url": "https://charmcityjs.org",
        "desc": "I'm a community organizer for charmCityJS, a Baltimore JavaScript meetup."
      }
    ],
    "items": ["Reading", "Cooking", "Baking"]
  }
}
